pyGizmos/__init__.py
pyGizmosPack/__init__.py
pyGizmos-0.0.4.dist-info/LICENSE
pyGizmos-0.0.4.dist-info/METADATA
pyGizmos-0.0.4.dist-info/WHEEL
pyGizmos-0.0.4.dist-info/top_level.txt
pyGizmos-0.0.4.dist-info/RECORD
